pansi/__init__.py
pansi/console.py
pansi-2020.7.3.dist-info/LICENSE
pansi-2020.7.3.dist-info/METADATA
pansi-2020.7.3.dist-info/WHEEL
pansi-2020.7.3.dist-info/entry_points.txt
pansi-2020.7.3.dist-info/top_level.txt
pansi-2020.7.3.dist-info/RECORD
